Moore_FSM_Seq_Dect/FSM_seq_detc.v
// Verilog project: Verilog code for Sequence Detector using Moore FSM
// The sequence being detected is "1011" or One Zero One One 
module Sequence_Detector_MOORE_Verilog(sequence_in,clock,reset,detector_out
    );
input clock; // clock signal
input reset; // reset input
input sequence_in; // binary input
output reg detector_out; // output of the sequence detector
parameter  Zero=3'b000, // "Zero" State
           One=3'b001, // "One" State
           OneZero=3'b011, // "OneZero" State
           OneZeroOne=3'b010, // "OnceZeroOne" State
           OneZeroOneOne=3'b110;// "OneZeroOneOne" State
reg [2:0] current_state, next_state; // current state and next state
// sequential memory of the Moore FSM
always @(posedge clock, posedge reset)
begin
 if(reset==1) 
 current_state <= Zero;// when reset=1, reset the state of the FSM to "Zero" State
 else
 current_state <= next_state; // otherwise, next state
end 
// combinational logic of the Moore FSM
// to determine next state 
always @(current_state,sequence_in)
begin
 case(current_state) 
 Zero:begin
  if(sequence_in==1)
   next_state = One;
  else
   next_state = Zero;
 end
 One:begin
  if(sequence_in==0)
   next_state = OneZero;
  else
   next_state = One;
 end
 OneZero:begin
  if(sequence_in==0)
   next_state = Zero;
  else
   next_state = OneZeroOne;
 end 
 OneZeroOne:begin
  if(sequence_in==0)
   next_state = OneZero;
  else
   next_state = OneZeroOneOne;
 end
 OneZeroOneOne:begin
  if(sequence_in==0)
   next_state = OneZero;
  else
   next_state = One;
 end
 default:next_state = Zero;
 endcase
end
// combinational logic to determine the output
// of the Moore FSM, output only depends on current state
always @(current_state)
begin 
 case(current_state) 
    Zero:   detector_out = 0;
    One:   detector_out = 0;
    OneZero:  detector_out = 0;
    OneZeroOne:  detector_out = 0;
    OneZeroOneOne:  detector_out = 1;
 default:  detector_out = 0;
 endcase
end 
endmodule

Moore_FSM_Seq_Dect/FSM_seq_detc_tb.v
`timescale 1ns/1ns
`include "FSM_seq_detc.v"

// Verilog project: Verilog code for Sequence Detector using Moore FSM
// Verilog Testbench for Sequence Detector using Moore FSM 
module tb_Sequence_Detector_Moore_FSM_Verilog;

 // Inputs
 reg sequence_in;
 reg clock;
 reg reset;

 // Outputs
 wire detector_out;

 // Instantiate the Sequence Detector using Moore FSM
 Sequence_Detector_MOORE_Verilog uut (
  .sequence_in(sequence_in), 
  .clock(clock), 
  .reset(reset), 
  .detector_out(detector_out)
 );

 always #5 clock = ~clock;
 
 initial begin
 clock = 0;
 end 

 initial begin

  $dumpfile("FSM_seq_detc_tb.vcd");
  $dumpvars(0,tb_Sequence_Detector_Moore_FSM_Verilog);
  // Initialize Inputs
  sequence_in = 0;
  reset = 1;
  // Wait 100 ns for global reset to finish
  #30;
      reset = 0;
  #40;
  sequence_in = 1;
  #10;
  sequence_in = 0;
  #10;
  sequence_in = 1; 
  #20;
  sequence_in = 0; 
  #20;
  sequence_in = 1; 
  #20;
  sequence_in = 0;  
  // Add stimulus here
  
  $display("Test Complete");
  $finish;
 end
      
endmodule

Moore_FSM_Seq_Dect/FSM_seq_detc_tb.vcd
$date
	Thu Jun 29 21:36:18 2023
$end
$version
	Icarus Verilog
$end
$timescale
	1ns
$end
$scope module tb_Sequence_Detector_Moore_FSM_Verilog $end
$var wire 1 ! detector_out $end
$var reg 1 " clock $end
$var reg 1 # reset $end
$var reg 1 $ sequence_in $end
$scope module uut $end
$var wire 1 " clock $end
$var wire 1 # reset $end
$var wire 1 $ sequence_in $end
$var parameter 3 % One $end
$var parameter 3 & OneZero $end
$var parameter 3 ' OneZeroOne $end
$var parameter 3 ( OneZeroOneOne $end
$var parameter 3 ) Zero $end
$var reg 3 * current_state [2:0] $end
$var reg 1 ! detector_out $end
$var reg 3 + next_state [2:0] $end
$upscope $end
$upscope $end
$enddefinitions $end
$comment Show the parameter values. $end
$dumpall
b0 )
b110 (
b10 '
b11 &
b1 %
$end
#0
$dumpvars
b0 +
b0 *
0$
1#
0"
0!
$end
#5
1"
#10
0"
#15
1"
#20
0"
#25
1"
#30
0"
0#
#35
1"
#40
0"
#45
1"
#50
0"
#55
1"
#60
0"
#65
1"
#70
b1 +
0"
1$
#75
b1 *
1"
#80
b11 +
0"
0$
#85
b0 +
b11 *
1"
#90
b10 +
0"
1$
#95
b110 +
b10 *
1"
#100
0"
#105
1!
b1 +
b110 *
1"
#110
b11 +
0"
0$
#115
0!
b0 +
b11 *
1"
#120
0"
#125
b0 *
1"
#130
b1 +
0"
1$
#135
b1 *
1"
#140
0"
#145
1"
#150
b11 +
0"
0$
