4_bit_counter/counter.v
module counter ( input clk,  //Declare input port for clock to allow counter to count up
                 input rstn, //Declare input port for reset to 0 when required
                 output reg [3:0] out); //Declare 4-bit output port to get the counter values

// This always block will be triggered at the rising edge of clk (0->1)
//Once inside this block, it checks if the reset is 0, if yes then change out to zero
// If reset is 1, then design should be allowed to count up, so increment counter

always @ (posedge clk) begin
    if (! rstn)
    out <=0;
    else
    out <= out +1;
end

endmodule

4_bit_counter/tb_counter.v
`timescale 1ps/1ps
`include "counter.v"


module tb_counter;
 reg clk;
 reg rstn;
 wire [3:0] out;

 //Instantiate counter design and connect with Testbench variables
 counter c0(.clk(clk),
            .rstn(rstn),
            .out(out));
 
 //Generate a clock that should be driven to design
 //This clock will flip its value every 5ns -> time period = 10ns -> freq 100MHz
 always #5 clk = ~clk;

 //This initial block forms the stimulus of the testbench
initial begin

     $dumpfile("tb_counter.vcd");
     $dumpvars(0,tb_counter);
    //1. Initialize testbench variables to 0 at start of simulation
    clk <= 0;
    rstn <= 0;

    //2.Drive rest of stimulus, reset is assert in between
    #20 rstn <= 1;
    #80 rstn <= 0;
    #50 rstn <= 1;

    //3. Finising the stimulus after 200ns
    #20 $finish;

    $display("Test Complete");
end

 

 endmodule

4_bit_counter/tb_counter.vcd
$date
	Tue Mar 28 00:14:36 2023
$end
$version
	Icarus Verilog
$end
$timescale
	1ps
$end
$scope module tb_counter $end
$var wire 4 ! out [3:0] $end
$var reg 1 " clk $end
$var reg 1 # rstn $end
$scope module c0 $end
$var wire 1 " clk $end
$var wire 1 # rstn $end
$var reg 4 $ out [3:0] $end
$upscope $end
$upscope $end
$enddefinitions $end
$comment Show the parameter values. $end
$dumpall
$end
#0
$dumpvars
bx $
0#
0"
bx !
$end
#5
b0 !
b0 $
1"
#10
0"
#15
1"
#20
1#
0"
#25
b1 !
b1 $
1"
#30
0"
#35
b10 !
b10 $
1"
#40
0"
#45
b11 !
b11 $
1"
#50
0"
#55
b100 !
b100 $
1"
#60
0"
#65
b101 !
b101 $
1"
#70
0"
#75
b110 !
b110 $
1"
#80
0"
#85
b111 !
b111 $
1"
#90
0"
#95
b1000 !
b1000 $
1"
#100
0#
0"
#105
b0 !
b0 $
1"
#110
0"
#115
1"
#120
0"
#125
1"
#130
0"
#135
1"
#140
0"
#145
1"
#150
1#
0"
#155
b1 !
b1 $
1"
#160
0"
#165
b10 !
b10 $
1"
