Finite_State_Machine/FSM.v
module FSM(

        input clk,

        input x,

        output y);

    reg [1:0] state;

    assign y = state[1] & state[0] & x;

    always @ (posedge clk)

        case (state)

            2'b00: state <= x?2'b01:2'b00; // If the current state is 2'b00, it checks the value of signal x. If x is true (non-zero), it transitions to state 2'b01; otherwise, it stays in state 2'b00

            2'b01: state <= x?2'b10:2'b00; // If the current state is 2'b01, it checks the value of signal x. If x is true (non-zero), it transitions to state 2'b10; otherwise, it stays in state 2'b00

            2'b10: state <= x?2'b11:2'b00; // If the current state is 2'b10, it checks the value of signal x. If x is true (non-zero), it transitions to state 2'b11; otherwise, it stays in state 2'b00

            2'b11: state <= 2'b00; // If the current state is 2'b11, it always transitions back to state 2'b00
            
            default: state <= 2'b00;
        endcase

endmodule

Finite_State_Machine/FSM_tb.v
`timescale 1ns/1ns
`include "FSM.v"

module FSM_tb;

  reg clk;
  reg x;
  wire y;

  FSM uut (
    .clk(clk),
    .x(x),
    .y(y)
  );

  initial begin

  $dumpfile("FSM_tb.vcd");
  $dumpvars(0,FSM_tb);

    clk = 0;
    x = 0;

    // Reset the state initially
    #5;
    x = 1;
    #5;
    x = 0;

    // Test case 1
    #5;
    x = 1;
    #5;
    x = 0;

    // Test case 2
    #5;
    x = 1;
    #5;
    x = 1;
    #5;
    x = 1;

    // Test case 3
    #5;
    x = 0;
    #5;
    x = 0;

    // Additional test cases
    // ...
    $display("Test Complete");
    $finish;
  end

  always #5 clk = ~clk;

endmodule

Finite_State_Machine/FSM_tb.vcd
$date
	Thu Jun 29 22:43:04 2023
$end
$version
	Icarus Verilog
$end
$timescale
	1ns
$end
$scope module FSM_tb $end
$var wire 1 ! y $end
$var reg 1 " clk $end
$var reg 1 # x $end
$scope module uut $end
$var wire 1 " clk $end
$var wire 1 # x $end
$var wire 1 ! y $end
$var reg 2 $ state [1:0] $end
$upscope $end
$upscope $end
$enddefinitions $end
$comment Show the parameter values. $end
$dumpall
$end
#0
$dumpvars
bx $
0#
0"
0!
$end
#5
b0 $
0!
1"
1#
#10
0"
0#
#15
b1 $
1"
1#
#20
0"
0#
#25
b10 $
1"
1#
#30
0"
#35
1!
b11 $
1"
#40
0!
0"
0#
#45
b0 $
1"
