4_bit_UpDown_counter/4_bit_UD_counter.v
// Verilog code for up-down counter
module up_down_counter(
    input clk,reset,up_down, output reg[3:0] counter
);
reg [3:0] counter_up_down;

//down counter
always @(posedge clk or posedge reset) begin
    if (reset) 
    counter_up_down <= 4'h0;
    else if(~up_down)
    counter_up_down <= counter_up_down + 4'd1;
    else
    counter_up_down <= counter_up_down - 4'd1;
    assign counter = counter_up_down;
end

    
endmodule

4_bit_UpDown_counter/4_bit_UD_counter_tb.v
`timescale 1ns/1ns
`include "4_bit_UD_counter.v"

module updowncounter_testbench();
reg clk,reset,up_down;
wire [3:0] counter;

up_down_counter dut(clk,reset,up_down,counter);

always   #5 clk=~clk;

initial begin

     $dumpfile("4_bit_UD_counter_tb.vcd");
     $dumpvars(0,updowncounter_testbench);

    clk=0;
    reset=1;
    up_down = 0;
    #20;
    reset=0;
    #200;
    up_down=1;
    //terminate simulation using $finish system task
    #500
    $display("Test Complete");
    $finish;
end
    
endmodule

4_bit_UpDown_counter/4_bit_UD_counter_tb.vcd
$date
	Wed Jun 28 15:21:31 2023
$end
$version
	Icarus Verilog
$end
$timescale
	1ns
$end
$scope module updowncounter_testbench $end
$var wire 4 ! counter [3:0] $end
$var reg 1 " clk $end
$var reg 1 # reset $end
$var reg 1 $ up_down $end
$scope module dut $end
$var wire 1 " clk $end
$var wire 1 # reset $end
$var wire 1 $ up_down $end
$var reg 4 % counter [3:0] $end
$var reg 4 & counter_up_down [3:0] $end
$upscope $end
$upscope $end
$enddefinitions $end
$comment Show the parameter values. $end
$dumpall
$end
#0
$dumpvars
b0 &
b0 %
0$
1#
0"
b0 !
$end
#5
1"
#10
0"
#15
1"
#20
0"
0#
#25
b1 !
b1 %
b1 &
1"
#30
0"
#35
b10 !
b10 %
b10 &
1"
#40
0"
#45
b11 !
b11 %
b11 &
1"
#50
0"
#55
b100 !
b100 %
b100 &
1"
#60
0"
#65
b101 !
b101 %
b101 &
1"
#70
0"
#75
b110 !
b110 %
b110 &
1"
#80
0"
#85
b111 !
b111 %
b111 &
1"
#90
0"
#95
b1000 !
b1000 %
b1000 &
1"
#100
0"
#105
b1001 !
b1001 %
b1001 &
1"
#110
0"
#115
b1010 !
b1010 %
b1010 &
1"
#120
0"
#125
b1011 !
b1011 %
b1011 &
1"
#130
0"
#135
b1100 !
b1100 %
b1100 &
1"
#140
0"
#145
b1101 !
b1101 %
b1101 &
1"
#150
0"
#155
b1110 !
b1110 %
b1110 &
1"
#160
0"
#165
b1111 !
b1111 %
b1111 &
1"
#170
0"
#175
b0 !
b0 %
b0 &
1"
#180
0"
#185
b1 !
b1 %
b1 &
1"
#190
0"
#195
b10 !
b10 %
b10 &
1"
#200
0"
#205
b11 !
b11 %
b11 &
1"
#210
0"
#215
b100 !
b100 %
b100 &
1"
#220
0"
1$
#225
b11 !
b11 %
b11 &
1"
#230
0"
#235
b10 !
b10 %
b10 &
1"
#240
0"
#245
b1 !
b1 %
b1 &
1"
#250
0"
#255
b0 !
b0 %
b0 &
1"
#260
0"
#265
b1111 !
b1111 %
b1111 &
1"
#270
0"
#275
b1110 !
b1110 %
b1110 &
1"
#280
0"
#285
b1101 !
b1101 %
b1101 &
1"
#290
0"
#295
b1100 !
b1100 %
b1100 &
1"
#300
0"
#305
b1011 !
b1011 %
b1011 &
1"
#310
0"
#315
b1010 !
b1010 %
b1010 &
1"
#320
0"
#325
b1001 !
b1001 %
b1001 &
1"
#330
0"
#335
b1000 !
b1000 %
b1000 &
1"
#340
0"
#345
b111 !
b111 %
b111 &
1"
#350
0"
#355
b110 !
b110 %
b110 &
1"
#360
0"
#365
b101 !
b101 %
b101 &
1"
#370
0"
#375
b100 !
b100 %
b100 &
1"
#380
0"
#385
b11 !
b11 %
b11 &
1"
#390
0"
#395
b10 !
b10 %
b10 &
1"
#400
0"
#405
b1 !
b1 %
b1 &
1"
#410
0"
#415
b0 !
b0 %
b0 &
1"
#420
0"
#425
b1111 !
b1111 %
b1111 &
1"
#430
0"
#435
b1110 !
b1110 %
b1110 &
1"
#440
0"
#445
b1101 !
b1101 %
b1101 &
1"
#450
0"
#455
b1100 !
b1100 %
b1100 &
1"
#460
0"
#465
b1011 !
b1011 %
b1011 &
1"
#470
0"
#475
b1010 !
b1010 %
b1010 &
1"
#480
0"
#485
b1001 !
b1001 %
b1001 &
1"
#490
0"
#495
b1000 !
b1000 %
b1000 &
1"
#500
0"
#505
b111 !
b111 %
b111 &
1"
#510
0"
#515
b110 !
b110 %
b110 &
1"
#520
0"
#525
b101 !
b101 %
b101 &
1"
#530
0"
#535
b100 !
b100 %
b100 &
1"
#540
0"
#545
b11 !
b11 %
b11 &
1"
#550
0"
#555
b10 !
b10 %
b10 &
1"
#560
0"
#565
b1 !
b1 %
b1 &
1"
#570
0"
#575
b0 !
b0 %
b0 &
1"
#580
0"
#585
b1111 !
b1111 %
b1111 &
1"
#590
0"
#595
b1110 !
b1110 %
b1110 &
1"
#600
0"
#605
b1101 !
b1101 %
b1101 &
1"
#610
0"
#615
b1100 !
b1100 %
b1100 &
1"
#620
0"
#625
b1011 !
b1011 %
b1011 &
1"
#630
0"
#635
b1010 !
b1010 %
b1010 &
1"
#640
0"
#645
b1001 !
b1001 %
b1001 &
1"
#650
0"
#655
b1000 !
b1000 %
b1000 &
1"
#660
0"
#665
b111 !
b111 %
b111 &
1"
#670
0"
#675
b110 !
b110 %
b110 &
1"
#680
0"
#685
b101 !
b101 %
b101 &
1"
#690
0"
#695
b100 !
b100 %
b100 &
1"
#700
0"
#705
b11 !
b11 %
b11 &
1"
#710
0"
#715
b10 !
b10 %
b10 &
1"
