Shift_register/shift_reg.v
module shift_reg #(
    parameter MSB=8
) (
    input d,
    input clk,
    input en,
    input dir,
    input reset,
    output reg [MSB-1:0] out
);

always @(posedge clk) begin
//This always block will "always" be triggered on the rising edge of clock
    if(!reset)
      out <= 0; // Once it enters the block, it will first check to see if reset is 0 and if yes then reset register
    else begin
        if(en) //If no, then check to see if the shift register is enabled
        case (dir)
            0 : out <= {out[MSB-2:0],d};
            1 : out <= {d, out[MSB-1:1]}; 
        endcase
        else // If no, maintain previous output. If yes, then shift based on requested direction
          out <= out;
    end
    
end
    
endmodule

Shift_register/shift_reg_tb.v
`timescale 1ns/1ns
`include "shift_reg.v"

module shift_reg_tb;
 parameter MSB =16;

 reg data;
 reg clk;
 reg en;
 reg dir;
 reg reset;
 wire [MSB-1:0] out;

//Initiate design (16-bit shift register) by passing MSB and connect with Testbench signals
 shift_reg #(MSB) sr0 (.d(data),
                       .clk(clk),
                       .en(en),
                       .dir(dir),
                       .reset(reset),
                       .out(out));
 always #10 clk = ~clk;

 initial begin
     $dumpfile("shift_reg_tb.vcd");
     $dumpvars(0,shift_reg_tb);

    clk <= 0;
    en <= 0;
    dir <= 0;
    reset <= 0;
    data <= 'h1;
 end

 initial begin

    //Apply reset and deassert reset after 10ns
    reset <= 0;
    #20 reset <= 1;
        en <= 1;
    //For 7 clock cycles, drive alternate vakues to data pin
    repeat (7) @ (posedge clk)
     data <= ~data;
    // Next 7 clock cycles, change shift direction and drive alternative values todata pin
    #10 dir <= 1;
    repeat (7) @ (posedge clk)
     data <= ~data;
    // Drive nothing for next 7 clocks, allow shift register to simply shift based on direction
    repeat (7) @ (posedge clk);

    $display("Test Complete");
    $finish;
 end
 initial
    $monitor ("reset=%b, data=%b, en=%b, dir=%b, out=%b",reset,data,en,dir,out);
    
endmodule

Shift_register/shift_reg_tb.vcd
$date
	Thu Jun 29 01:00:58 2023
$end
$version
	Icarus Verilog
$end
$timescale
	1ns
$end
$scope module shift_reg_tb $end
$var wire 16 ! out [15:0] $end
$var parameter 32 " MSB $end
$var reg 1 # clk $end
$var reg 1 $ data $end
$var reg 1 % dir $end
$var reg 1 & en $end
$var reg 1 ' reset $end
$scope module sr0 $end
$var wire 1 # clk $end
$var wire 1 $ d $end
$var wire 1 % dir $end
$var wire 1 & en $end
$var wire 1 ' reset $end
$var parameter 32 ( MSB $end
$var reg 16 ) out [15:0] $end
$upscope $end
$upscope $end
$enddefinitions $end
$comment Show the parameter values. $end
$dumpall
b10000 (
b10000 "
$end
#0
$dumpvars
bx )
0'
0&
0%
1$
0#
bx !
$end
#10
b0 !
b0 )
1#
#20
1&
1'
0#
#30
b1 !
b1 )
0$
1#
#40
0#
#50
1$
b10 !
b10 )
1#
#60
0#
#70
b101 !
b101 )
0$
1#
#80
0#
#90
1$
b1010 !
b1010 )
1#
#100
0#
#110
b10101 !
b10101 )
0$
1#
#120
0#
#130
1$
b101010 !
b101010 )
1#
#140
0#
#150
b1010101 !
b1010101 )
0$
1#
#160
1%
0#
#170
b101010 !
b101010 )
1$
1#
#180
0#
#190
0$
b1000000000010101 !
b1000000000010101 )
1#
#200
0#
#210
b100000000001010 !
b100000000001010 )
1$
1#
#220
0#
#230
0$
b1010000000000101 !
b1010000000000101 )
1#
#240
0#
#250
b101000000000010 !
b101000000000010 )
1$
1#
#260
0#
#270
0$
b1010100000000001 !
b1010100000000001 )
1#
#280
0#
#290
b101010000000000 !
b101010000000000 )
1$
1#
#300
0#
#310
b1010101000000000 !
b1010101000000000 )
1#
#320
0#
#330
b1101010100000000 !
b1101010100000000 )
1#
#340
0#
#350
b1110101010000000 !
b1110101010000000 )
1#
#360
0#
#370
b1111010101000000 !
b1111010101000000 )
1#
#380
0#
#390
b1111101010100000 !
b1111101010100000 )
1#
#400
0#
#410
b1111110101010000 !
b1111110101010000 )
1#
#420
0#
#430
b1111111010101000 !
b1111111010101000 )
1#
